Workbook
Name aporte: 'Projeto Imobiliário'!$D$19
Name qtd_anos: 'Projeto Imobiliário'!$D$20
Name rendimento_carteira: 'Projeto Imobiliário'!$D$15

Sheet Projeto Imobiliário
B13: CONFIGURAÇÕES
B14: SALÁRIO | D14: 2000
B15: RENDIMENTO CARTEIRA | D15: 0.006
B16: SUJESTÃO DE INVESTIMENTO (30%) | D16: =D14*30% -> 600
B18: INVESTIMENTO MENSAL
B19: INVESTIMENTO POR MÊS? | D19: 200
B20: PRETENSÃO ANUAL PARA INVESTIMENTO? | D20: 5
B21: TAXA DE RENDIMENTO MENSAL? | D21: 0.01079
B22: PATRIMÔNIO ACUMULADO | D22: =FV(D21,D20*12,D19*-1) -> 16755.383
B23: DIVIDENDO MENSAL | D23: =D22*$D$15 -> 100.5323
B25: CENÁRIOS- PATRIMÔNIO ACUMULADO/DIVIDENDO
A26: 2 | B26: QUANTO EM 2 ANOS? | C26: =FV($D$21,$A26*12,$D$19*-1) -> 5445.5255 | D26: =C26*$D$15 -> 32.673153
A27: 5 | B27: QUANTO EM 5 ANOS? | C27: =FV($D$21,$A27*12,$D$19*-1) -> 16755.383 | D27: =C27*$D$15 -> 100.5323
A28: 10 | B28: QUANTO EM 10 ANOS? | C28: =FV($D$21,$A28*12,$D$19*-1) -> 48656.843 | D28: =C28*$D$15 -> 291.94106
A29: 20 | B29: QUANTO EM 20 ANOS? | C29: =FV($D$21,$A29*12,$D$19*-1) -> 225039.68 | D29: =C29*$D$15 -> 1350.2381
A30: 30 | B30: QUANTO EM 30 ANOS? | C30: =FV($D$21,$A30*12,$D$19*-1) -> 864433.93 | D30: =C30*$D$15 -> 5186.6036
B33: PERFIL | C33: MODERADO
B34: VALOR A SER IINVESTIDO POR MÊS | C34: =aporte -> 200
B37: TIPO DE FII | C37: PERCENTUAL SUGERIDO | D37: VALORES
B38: PAPEL | C38: =VLOOKUP($C$33&"-"&B38,APOIO!$B:$E,4,FALSE) -> 0.32 | D38: =C38*$C$34 -> 64
B39: TIJOLO | C39: =VLOOKUP($C$33&"-"&B39,APOIO!$B:$E,4,FALSE) -> 0.35 | D39: =C39*$C$34 -> 70
B40: HÍBRIDOS | C40: =VLOOKUP($C$33&"-"&B40,APOIO!$B:$E,4,FALSE) -> 0.08 | D40: =C40*$C$34 -> 16
B41: FOFs | C41: =VLOOKUP($C$33&"-"&B41,APOIO!$B:$E,4,FALSE) -> 0.1 | D41: =C41*$C$34 -> 20
B42: DESENVOLVIMENTO | C42: =VLOOKUP($C$33&"-"&B42,APOIO!$B:$E,4,FALSE) -> 0.1 | D42: =C42*$C$34 -> 20
B43: HOTELARIAS | C43: =VLOOKUP($C$33&"-"&B43,APOIO!$B:$E,4,FALSE) -> 0.1 | D43: =C43*$C$34 -> 20
B44: TOTAL | D44: =SUM(D38:D43) -> 210

Sheet APOIO
B2: CHAVE | C2: PERFIL | D2: TIPO DE FII | E2: PERCENTUAL
B3: =C3&"-"&D3 -> CONSERVADOR-PAPEL | C3: CONSERVADOR | D3: PAPEL | E3: 0.3 | G3: CONSERVADOR-TIJOLO | I3: =VLOOKUP(G3,$B:$E,4,FALSE) -> 0.5
B4: =C4&"-"&D4 -> CONSERVADOR-TIJOLO | C4: CONSERVADOR | D4: TIJOLO | E4: 0.5
B5: =C5&"-"&D5 -> CONSERVADOR-HÍBRIDOS | C5: CONSERVADOR | D5: HÍBRIDOS | E5: 0.1
B6: =C6&"-"&D6 -> CONSERVADOR-FOFs | C6: CONSERVADOR | D6: FOFs | E6: 0.1
B7: =C7&"-"&D7 -> CONSERVADOR-DESENVOLVIMENTO | C7: CONSERVADOR | D7: DESENVOLVIMENTO | E7: 0
B8: =C8&"-"&D8 -> CONSERVADOR-HOTELARIAS | C8: CONSERVADOR | D8: HOTELARIAS | E8: 0
B9: =C9&"-"&D9 -> MODERADO-PAPEL | C9: MODERADO | D9: PAPEL | E9: 0.32
B10: =C10&"-"&D10 -> MODERADO-TIJOLO | C10: MODERADO | D10: TIJOLO | E10: 0.35
B11: =C11&"-"&D11 -> MODERADO-HÍBRIDOS | C11: MODERADO | D11: HÍBRIDOS | E11: 0.08
B12: =C12&"-"&D12 -> MODERADO-FOFs | C12: MODERADO | D12: FOFs | E12: 0.1
B13: =C13&"-"&D13 -> MODERADO-DESENVOLVIMENTO | C13: MODERADO | D13: DESENVOLVIMENTO | E13: 0.1
B14: =C14&"-"&D14 -> MODERADO-HOTELARIAS | C14: MODERADO | D14: HOTELARIAS | E14: 0.1
B15: =C15&"-"&D15 -> AGRESSIVO-PAPEL | C15: AGRESSIVO | D15: PAPEL | E15: 0.5
... B20: =C20&"-"&D20 -> AGRESSIVO-HOTELARIAS | C20: AGRESSIVO | D20: HOTELARIAS | E20: 0.1
